{
  "sections": {
    "template": {
      "type": "text-block",
      "blocks": {
        "210f6884-0e4d-4ab5-8aa0-bbf3418c0ca4": {
          "type": "block",
          "settings": {
            "block-title": "",
            "block-description": "<p>Wij hanteren een retourbeleid van 14 dagen, wat betekent dat u 14 dagen de tijd heeft na ontvangst van uw artikel om een retour aan te vragen.<br\/><\/p>"
          }
        }
      },
      "block_order": [
        "210f6884-0e4d-4ab5-8aa0-bbf3418c0ca4"
      ],
      "settings": {
        "title": "Terugbetalingsbeleid",
        "button-label": "Check de nieuwste trends",
        "button-url": ""
      }
    }
  },
  "order": [
    "template"
  ]
}
